dstvparser/__init__.py
dstvparser/models/__init__.py
dstvparser/models/nc_part.py
dstvparser/parsers/__init__.py
dstvparser/parsers/dstv_file_parser.py
dstvparser/parsers/factory.py
dstvparser/parsers/nc1_file_parser.py
dstvparser/parsers/nc_file_parser.py
dstvparser/utils/__init__.py
dstvparser/utils/faces_name_schemas.py
dstvparser/utils/profile_schemas.py
dstvparser/utils/utilities.py
dstvparser-0.1.2.dist-info/METADATA
dstvparser-0.1.2.dist-info/WHEEL
dstvparser-0.1.2.dist-info/top_level.txt
dstvparser-0.1.2.dist-info/RECORD
