Metadata-Version: 2.4
Name: dstvparser
Version: 0.1.2
Summary: DSTV file parser (core library)
Author-email: Federico Sidraschi <smia46@virgilio.it>
Keywords: DSTV,dstv,tekla,advance steel,parsing,automation,batch-processing,manufacturing,cnc,cam,design-automation,cad-automation,technical-drawing,mechanical-design,steel profiles
Requires-Python: >=3.9
Provides-Extra: dev
Requires-Dist: pytest; extra == "dev"
Requires-Dist: black; extra == "dev"
Requires-Dist: ruff; extra == "dev"
